datamintapi/__init__.py
datamintapi-0.0.post1.dist-info/METADATA
datamintapi-0.0.post1.dist-info/WHEEL
datamintapi-0.0.post1.dist-info/top_level.txt
datamintapi-0.0.post1.dist-info/RECORD
