Metadata-Version: 2.4
Name: datamintapi
Version: 0.0.post1
Summary: Transitional package - use 'datamint' instead
Project-URL: Homepage, https://github.com/SonanceAI/datamint-python-api
Project-URL: Repository, https://github.com/SonanceAI/datamint-python-api
Classifier: Development Status :: 7 - Inactive
Classifier: Intended Audience :: Developers
Classifier: Programming Language :: Python :: 3
Classifier: Programming Language :: Python :: 3.10
Classifier: Programming Language :: Python :: 3.11
Classifier: Programming Language :: Python :: 3.12
Classifier: Programming Language :: Python :: 3.13
Requires-Python: >=3.7
